[
  {
    "text": "hello is anybody there",
    "entities": [],
    "predicted_entities": [
      {
        "entity": "name",
        "start": 9,
        "end": 22,
        "confidence_entity": 0.9439981493994013,
        "value": "anybody there",
        "extractor": "CRFEntityExtractor"
      }
    ]
  },
  {
    "text": "toodle-oo",
    "entities": [],
    "predicted_entities": [
      {
        "entity": "name",
        "start": 0,
        "end": 9,
        "confidence_entity": 0.6915867283254087,
        "value": "toodle-oo",
        "extractor": "CRFEntityExtractor"
      }
    ]
  },
  {
    "text": "waleed",
    "entities": [
      {
        "start": 0,
        "end": 6,
        "value": "waleed",
        "entity": "name"
      }
    ],
    "predicted_entities": []
  },
  {
    "text": "leila daghfous",
    "entities": [
      {
        "start": 0,
        "end": 14,
        "value": "leila daghfous",
        "entity": "name"
      }
    ],
    "predicted_entities": []
  },
  {
    "text": "Anis",
    "entities": [
      {
        "start": 0,
        "end": 4,
        "value": "Anis",
        "entity": "name"
      }
    ],
    "predicted_entities": []
  },
  {
    "text": "suleiman",
    "entities": [
      {
        "start": 0,
        "end": 8,
        "value": "suleiman",
        "entity": "name"
      }
    ],
    "predicted_entities": []
  },
  {
    "text": "houssem ghorbel",
    "entities": [
      {
        "start": 0,
        "end": 15,
        "value": "houssem ghorbel",
        "entity": "name"
      }
    ],
    "predicted_entities": []
  },
  {
    "text": "naima",
    "entities": [
      {
        "start": 0,
        "end": 5,
        "value": "naima",
        "entity": "name"
      }
    ],
    "predicted_entities": []
  },
  {
    "text": "minica blanco",
    "entities": [
      {
        "start": 0,
        "end": 13,
        "value": "minica blanco",
        "entity": "name"
      }
    ],
    "predicted_entities": []
  },
  {
    "text": "nada nefzi",
    "entities": [
      {
        "start": 0,
        "end": 10,
        "value": "nada nefzi",
        "entity": "name"
      }
    ],
    "predicted_entities": []
  },
  {
    "text": "kamel tounsi",
    "entities": [
      {
        "start": 0,
        "end": 12,
        "value": "kamel tounsi",
        "entity": "name"
      }
    ],
    "predicted_entities": []
  },
  {
    "text": "build chatbot",
    "entities": [
      {
        "start": 0,
        "end": 13,
        "value": "build chatbot",
        "entity": "stream_name"
      }
    ],
    "predicted_entities": []
  },
  {
    "text": "financial independence calculator",
    "entities": [
      {
        "start": 0,
        "end": 33,
        "value": "financial independence calculator",
        "entity": "workspace_name"
      }
    ],
    "predicted_entities": []
  },
  {
    "text": "ws chatbot backbones creation",
    "entities": [
      {
        "start": 0,
        "end": 29,
        "value": "ws chatbot backbones creation",
        "entity": "task_name"
      }
    ],
    "predicted_entities": [
      {
        "entity": "workspace_name",
        "start": 0,
        "end": 29,
        "confidence_entity": 0.4725716567436877,
        "value": "ws chatbot backbones creation",
        "extractor": "CRFEntityExtractor"
      }
    ]
  },
  {
    "text": "editor",
    "entities": [
      {
        "start": 0,
        "end": 6,
        "value": "editor",
        "entity": "workspace_name"
      }
    ],
    "predicted_entities": []
  },
  {
    "text": "IOT Platform Data Modeling Architect",
    "entities": [
      {
        "start": 0,
        "end": 36,
        "value": "IOT Platform Data Modeling Architect",
        "entity": "stream_name"
      }
    ],
    "predicted_entities": []
  },
  {
    "text": "Build First Node App",
    "entities": [
      {
        "start": 0,
        "end": 20,
        "value": "Build First Node App",
        "entity": "workspace_name"
      }
    ],
    "predicted_entities": []
  },
  {
    "text": "A spam classifier",
    "entities": [
      {
        "start": 0,
        "end": 17,
        "value": "A spam classifier",
        "entity": "workspace_name"
      }
    ],
    "predicted_entities": []
  },
  {
    "text": "Troubleshoot",
    "entities": [
      {
        "start": 0,
        "end": 12,
        "value": "Troubleshoot",
        "entity": "task_name"
      }
    ],
    "predicted_entities": []
  },
  {
    "text": "A big portion of modern software is SaaS and web apps",
    "entities": [
      {
        "start": 0,
        "end": 53,
        "value": "A big portion of modern software is SaaS and web apps",
        "entity": "workspace_name"
      }
    ],
    "predicted_entities": [
      {
        "entity": "workspace_description",
        "start": 0,
        "end": 53,
        "confidence_entity": 0.5826391433926384,
        "value": "A big portion of modern software is SaaS and web apps",
        "extractor": "CRFEntityExtractor"
      }
    ]
  },
  {
    "text": "Achieving Quality of Service and Quality of Life in the Grid",
    "entities": [
      {
        "start": 0,
        "end": 60,
        "value": "Achieving Quality of Service and Quality of Life in the Grid",
        "entity": "workspace_description"
      }
    ],
    "predicted_entities": [
      {
        "entity": "workspace_description",
        "start": 0,
        "end": 55,
        "confidence_entity": 0.4097341181088932,
        "value": "Achieving Quality of Service and Quality of Life in the",
        "extractor": "CRFEntityExtractor"
      }
    ]
  },
  {
    "text": "548",
    "entities": [
      {
        "start": 0,
        "end": 3,
        "value": "548",
        "entity": "org_id"
      }
    ],
    "predicted_entities": []
  },
  {
    "text": "web application creation using node js",
    "entities": [
      {
        "start": 0,
        "end": 38,
        "value": "web application creation using node js",
        "entity": "workspace_description"
      }
    ],
    "predicted_entities": [
      {
        "entity": "workspace_name",
        "start": 0,
        "end": 38,
        "confidence_entity": 0.41123464696192785,
        "value": "web application creation using node js",
        "extractor": "CRFEntityExtractor"
      }
    ]
  },
  {
    "text": "migration for the test environment",
    "entities": [
      {
        "start": 0,
        "end": 34,
        "value": "migration for the test environment",
        "entity": "workspace_description"
      }
    ],
    "predicted_entities": []
  },
  {
    "text": "1281",
    "entities": [
      {
        "start": 0,
        "end": 4,
        "value": "1281",
        "entity": "stream_id"
      }
    ],
    "predicted_entities": []
  },
  {
    "text": "extract source code from a small exe file",
    "entities": [
      {
        "start": 0,
        "end": 41,
        "value": "extract source code from a small exe file",
        "entity": "stream_name"
      }
    ],
    "predicted_entities": []
  },
  {
    "text": "General Workspace",
    "entities": [
      {
        "start": 0,
        "end": 17,
        "value": "General Workspace",
        "entity": "workspace_type"
      }
    ],
    "predicted_entities": []
  },
  {
    "text": "complete the major phases of the lifecycle",
    "entities": [
      {
        "start": 0,
        "end": 42,
        "value": "complete the major phases of the lifecycle",
        "entity": "task_name"
      }
    ],
    "predicted_entities": [
      {
        "entity": "stream_name",
        "start": 0,
        "end": 42,
        "confidence_entity": 0.5373414399867632,
        "value": "complete the major phases of the lifecycle",
        "extractor": "CRFEntityExtractor"
      }
    ]
  },
  {
    "text": "foundational knowledge of project",
    "entities": [
      {
        "start": 0,
        "end": 33,
        "value": "foundational knowledge of project",
        "entity": "task_name"
      }
    ],
    "predicted_entities": []
  },
  {
    "text": "web app",
    "entities": [
      {
        "start": 0,
        "end": 7,
        "value": "web app",
        "entity": "workspace_name"
      }
    ],
    "predicted_entities": []
  }
]